pymore/__init__.py
pymore/equals_tester.py
pymore/equals_tester_test.py
pymore/iterators.py
pymore/iterators_test.py
pymore/py.typed
pymore-0.1.5.dist-info/licenses/LICENSE
pymore-0.1.5.dist-info/licenses/NOTICES
pymore-0.1.5.dist-info/METADATA
pymore-0.1.5.dist-info/WHEEL
pymore-0.1.5.dist-info/top_level.txt
pymore-0.1.5.dist-info/RECORD
