Metadata-Version: 2.4
Name: pymore
Version: 0.1.5
Summary: Mo python, less problems. Helpful python utilities.
Home-page: http://github.com/dabacon/pymore
Author: The pymore Developers
Author-email: dabacon@gmail.com
License: Apache 2
Keywords: python,testing,iterators
Classifier: Intended Audience :: Developers
Classifier: Programming Language :: Python :: 3.9
Classifier: Programming Language :: Python :: 3.10
Classifier: Programming Language :: Python :: 3.11
Classifier: Programming Language :: Python :: 3.12
Classifier: Programming Language :: Python :: 3.13
Classifier: License :: OSI Approved :: Apache Software License
Classifier: Operating System :: OS Independent
Classifier: Typing :: Typed
Requires-Python: >=3.9.0
License-File: LICENSE
License-File: NOTICES
Provides-Extra: dev-env
Requires-Dist: black; extra == "dev-env"
Requires-Dist: mypy; extra == "dev-env"
Requires-Dist: pytest; extra == "dev-env"
Requires-Dist: twine; extra == "dev-env"
Dynamic: author
Dynamic: author-email
Dynamic: classifier
Dynamic: description
Dynamic: description-content-type
Dynamic: home-page
Dynamic: keywords
Dynamic: license
Dynamic: license-file
Dynamic: provides-extra
Dynamic: requires-python
Dynamic: summary
